README.rst
qt5reactor.py
setup.py
qt5reactor_fork.egg-info/PKG-INFO
qt5reactor_fork.egg-info/SOURCES.txt
qt5reactor_fork.egg-info/dependency_links.txt
qt5reactor_fork.egg-info/requires.txt
qt5reactor_fork.egg-info/top_level.txt