Metadata-Version: 1.1
Name: qt5reactor-fork
Version: 0.1
Summary: Twisted Qt Integration
Home-page: https://github.com/sunu/qt5reactor
Author: Tarashish Mishra
Author-email: sunu@sunu.in
License: MIT
Keywords: Qt,twisted
Platform: UNKNOWN
Classifier: Development Status :: 3 - Alpha
Classifier: Environment :: X11 Applications :: Qt
Classifier: Framework :: Twisted
Classifier: Intended Audience :: Developers
Classifier: License :: OSI Approved :: MIT License
Classifier: Operating System :: OS Independent
Classifier: Programming Language :: Python
Classifier: Programming Language :: Python :: 2
Classifier: Programming Language :: Python :: 2.6
Classifier: Programming Language :: Python :: 2.7
Classifier: Natural Language :: English
Classifier: Topic :: Software Development :: Libraries :: Python Modules
